{
    "Name": "order-durations",
    "DataSourceType": "Event Hub",
    "EventHubProperties": {
        "ServiceBusNamespace": "genetec-events",
        "EventHubName": "order-durations",
        "SharedAccessPolicyName": "asa",
        "SharedAccessPolicyKey": "********",
        "PartitionKey": "",
        "PropertyColumns": [],
        "AuthenticationMode": "ConnectionString"
    },
    "DataSourceCredentialDomain": "5468f63c-825e-44a7-9a99-5bc3b73dd9c3.StreamAnalystics",
    "Serialization": {
        "Type": "Json",
        "Encoding": "UTF8",
        "Format": "LineSeparated"
    },
    "ScriptType": "Output"
}